inline_requests/__init__.py
inline_requests/generator.py
inline_requests/utils.py
scrapy_inline_requests-0.3.1.dist-info/DESCRIPTION.rst
scrapy_inline_requests-0.3.1.dist-info/METADATA
scrapy_inline_requests-0.3.1.dist-info/RECORD
scrapy_inline_requests-0.3.1.dist-info/WHEEL
scrapy_inline_requests-0.3.1.dist-info/metadata.json
scrapy_inline_requests-0.3.1.dist-info/top_level.txt
