Metadata-Version: 1.1
Name: scrapy-inline-requests
Version: 0.3.1
Summary: A decorator for writing coroutine-like spider callbacks.
Home-page: https://github.com/rolando/scrapy-inline-requests
Author: Rolando Espinoza
Author-email: rolando at rmax.io
License: MIT
Keywords: scrapy-inline-requests
Platform: UNKNOWN
Classifier: Development Status :: 4 - Beta
Classifier: Intended Audience :: Developers
Classifier: License :: OSI Approved :: MIT License
Classifier: Natural Language :: English
Classifier: Programming Language :: Python :: 2
Classifier: Programming Language :: Python :: 2.7
Classifier: Programming Language :: Python :: 3
Classifier: Programming Language :: Python :: 3.4
Classifier: Programming Language :: Python :: 3.5
